dynamicopy/LMDZ_files_manip.py
dynamicopy/__init__.py
dynamicopy/basins.py
dynamicopy/cartoplot.py
dynamicopy/compute.py
dynamicopy/cyclones.py
dynamicopy/grid.py
dynamicopy/ncload.py
dynamicopy/plot.py
dynamicopy/tc_maps.py
dynamicopy/tc_metrics.py
dynamicopy/utils.py
dynamicopy/utils_geo.py
dynamicopy/_data/ibtracs.since1980.cleaned.csv
dynamicopy/data/ibtracs.since1980.cleaned.csv
dynamicopy/tc/CPS.py
dynamicopy/tc/ET.py
dynamicopy/tc/STJ.py
dynamicopy/tc/Z21.py
dynamicopy/tc/__init__.py
dynamicopy/tc/_basins.py
dynamicopy/tc/hart.py
dynamicopy/tc/ibtracs.py
dynamicopy/tc/lifecycle.py
dynamicopy/tc/load_tracks.py
dynamicopy/tc/maps.py
dynamicopy/tc/matching.py
dynamicopy/tc/metrics.py
dynamicopy/tc/utils.py
dynamicopy-0.6.6.dist-info/LICENSE
dynamicopy-0.6.6.dist-info/METADATA
dynamicopy-0.6.6.dist-info/WHEEL
dynamicopy-0.6.6.dist-info/top_level.txt
dynamicopy-0.6.6.dist-info/RECORD
